myPYPI9/__init__.py
myPYPI9/prime_numbers.py
myPYPI9/prime_numbersNew.py
mypypi9-0.7.31.dist-info/licenses/LICENSE
mypypi9-0.7.31.dist-info/METADATA
mypypi9-0.7.31.dist-info/WHEEL
mypypi9-0.7.31.dist-info/top_level.txt
mypypi9-0.7.31.dist-info/RECORD
