Metadata-Version: 2.4
Name: myPYPI9
Version: 0.7.31
Summary: A lightweight Python library for prime number operations
Home-page: https://github.com/myNKUST/myprimelib9b
Author: timenet2300
Author-email: endersu@outlook.com
Project-URL: Documentation, https://github.com/myNKUST/myprimelib9b/wiki
Project-URL: Source, https://github.com/myNKUST/myprimelib9b
Keywords: primes mathematics algorithms
Classifier: Development Status :: 4 - Beta
Classifier: Intended Audience :: Developers
Classifier: Intended Audience :: Education
Classifier: Programming Language :: Python :: 3
Classifier: Programming Language :: Python :: 3.6
Classifier: Programming Language :: Python :: 3.7
Classifier: Programming Language :: Python :: 3.8
Classifier: Programming Language :: Python :: 3.9
Classifier: Operating System :: OS Independent
Classifier: Topic :: Scientific/Engineering :: Mathematics
Requires-Python: >=3.6
License-File: LICENSE
Dynamic: author
Dynamic: author-email
Dynamic: classifier
Dynamic: description
Dynamic: description-content-type
Dynamic: home-page
Dynamic: keywords
Dynamic: license-file
Dynamic: project-url
Dynamic: requires-python
Dynamic: summary
